mcmder/__init__.py
mcmder/errors.py
mcmder/mcmder.py
mcmder/utils.py
mcmder-0.2.0.dist-info/LICENSE
mcmder-0.2.0.dist-info/METADATA
mcmder-0.2.0.dist-info/WHEEL
mcmder-0.2.0.dist-info/top_level.txt
mcmder-0.2.0.dist-info/RECORD
