Metadata-Version: 2.1
Name: mcmder
Version: 0.2.0
Summary: Yet Another Wrapper of Nysol M-Command in Python.
Home-page: https://github.com/yhay81/mcmder
Author: Yusuke Hayashi
Author-email: yusuke8h@gmail.com
License: MIT
Platform: UNKNOWN
Classifier: License :: OSI Approved :: MIT License
Classifier: Programming Language :: Python
Classifier: Programming Language :: Python :: 3
Classifier: Programming Language :: Python :: Implementation :: CPython
Classifier: Programming Language :: Python :: Implementation :: PyPy
Requires-Python: >=3.5.0
Requires-Dist: pandas
